ccmodel/__config__/__init__.py
ccmodel/__config__/ccmodel_config.py
ccmodel/__config__/clang_config.py
ccmodel/__init__.py
ccmodel/ccm.py
ccmodel/code_models/__init__.py
ccmodel/code_models/basic.py
ccmodel/code_models/header.py
ccmodel/code_models/pointers.py
ccmodel/code_models/variants.py
ccmodel/reader.py
ccmodel/rules/__init__.py
ccmodel/rules/code_model_map.py
ccmodel/utils/__init__.py
ccmodel/utils/code_utils.py
ccmodel/utils/files.py
ccmodel-0.1.1.dist-info/entry_points.txt
ccmodel-0.1.1.dist-info/WHEEL
ccmodel-0.1.1.dist-info/METADATA
ccmodel-0.1.1.dist-info/LICENSE
ccmodel-0.1.1.dist-info/RECORD
