Metadata-Version: 2.1
Name: ccmodel
Version: 0.1.1
Summary: Clang-10 powered C/C++ code modeling
License: MIT
Keywords: c,cc,c++,cpp,parse,code,model
Author-email: Gabe Ingram <gabriel.ingram@colorado.edu>
Requires-Python: >=3.8
Classifier: License :: OSI Approved :: MIT License
Classifier: Programming Language :: Python :: 3
Classifier: Programming Language :: Python :: 3.10
Classifier: Programming Language :: Python :: 3.8
Classifier: Programming Language :: Python :: 3.9
Requires-Dist: ccm-clang-tools~=0.1
Requires-Dist: docker~=5.0
Requires-Dist: graphlib-backport~=1.0
Requires-Dist: loguru~=0.5
Requires-Dist: orjson~=3.6
Requires-Dist: regex~=2021.10
Project-URL: homepage, https://github.com/gjingram/ccmodel
Project-URL: repository, https://github.com/gjingram/ccmodel
